view_selection_python/__init__.py
view_selection_python/CLI.py
view_selection_python/ConfigCostEstimator.py
view_selection_python/ConfigurationGenerator.py
view_selection_python/CostEstimatorSinglePlan.py
view_selection_python/CwdChecker.py
view_selection_python/DbtProjectScraper.py
view_selection_python/Exceptions/errors.py
view_selection_python/FudgeFactorCalculator.py
view_selection_python/main.py
view_selection_python/ModelInfoManager.py
view_selection_python/OutputPrinter.py
view_selection_python/PostgresHandler.py
view_selection_python/ProfilesScraper.py
view_selection_python/SQLRewriter.py
view_selection_python/ViewSelectionAdvisor.py
view_selection_python/YamlScraper.py
view_selection_python-0.1.7.dist-info/entry_points.txt
view_selection_python-0.1.7.dist-info/METADATA
view_selection_python-0.1.7.dist-info/WHEEL
view_selection_python-0.1.7.dist-info/RECORD
