Metadata-Version: 2.1
Name: view-selection-python
Version: 0.1.7
Summary: View Selection Tool for dbt (python part)
Home-page: https://github.com/bramreinders97/view_selection_tool_python
License: MIT
Keywords: view,selection
Author: Bram Reinders
Author-email: bram.reinders@blenddata.nl
Requires-Python: >=3.11.5,<4.0.0
Classifier: License :: OSI Approved :: MIT License
Classifier: Programming Language :: Python :: 3
Requires-Dist: click (>=8.1.7,<9.0.0)
Requires-Dist: psycopg2 (>=2.9.9,<3.0.0)
Requires-Dist: ruamel-yaml (>=0.18.6,<0.19.0)
Requires-Dist: tabulate (>=0.9.0,<0.10.0)
Requires-Dist: tqdm (>=4.66.4,<5.0.0)
Project-URL: Repository, https://github.com/bramreinders97/view_selection_tool_python
